{
    "operations": {},
    "tasks": {
        "@taqueria/plugin-ligo.compile-all.1679590915898": {
            "task": "compile-all",
            "plugin": "@taqueria/plugin-ligo",
            "time": 1679590915898,
            "output": [
                {
                    "contract": "pokeGame.jsligo",
                    "artifact": "artifacts/pokeGame.tz"
                },
                {
                    "contract": "pokeGame.storageList.jsligo",
                    "artifact": "artifacts/pokeGame.default_storage.tz\n"
                },
                {
                    "contract": "pokeGame.parameterList.jsligo",
                    "artifact": "artifacts/pokeGame.parameter.default_parameter.tz\n"
                }
            ]
        },
        "@taqueria/plugin-tezos-client.simulate.1679590948514": {
            "task": "simulate",
            "plugin": "@taqueria/plugin-tezos-client",
            "time": 1679590948514,
            "output": [
                {
                    "contract": "pokeGame.tz",
                    "result": "Invalid"
                }
            ]
        },
        "@taqueria/plugin-tezos-client.simulate.1679591047444": {
            "task": "simulate",
            "plugin": "@taqueria/plugin-tezos-client",
            "time": 1679591047444,
            "output": [
                {
                    "contract": "pokeGame.tz",
                    "result": "Invalid"
                }
            ]
        }
    }
}